kexporter/__init__.py
kexporter/exporter.py
kexporter/static/style.css
kexporter/templates/base.html
kexporter-0.1.7.3.dist-info/licenses/LICENSE
kexporter-0.1.7.3.dist-info/METADATA
kexporter-0.1.7.3.dist-info/WHEEL
kexporter-0.1.7.3.dist-info/top_level.txt
kexporter-0.1.7.3.dist-info/RECORD
