Metadata-Version: 2.4
Name: kexporter
Version: 0.1.7.3
Summary: Module d'exportation de salons discord en fichier HTML (Discord.py)
Author-email: Kushh <kushy.lade@gmail.com>
License:                     GNU GENERAL PUBLIC LICENSE
Keywords: discord,html,export
License-File: LICENSE
Requires-Dist: discord.py>=2.5.2
Requires-Dist: jinja2>=3.1.6
Dynamic: license-file
